<col:collection xmlns="http://cnx.rice.edu/collxml" xmlns:col="http://cnx.rice.edu/collxml" xml:lang="en" type="Course">  <metadata xmlns:md="http://cnx.rice.edu/mdml" mdml-version="0.5">  <md:content-id>col11368</md:content-id>  <md:title>Madlavning</md:title>      <md:license url="http://creativecommons.org/licenses/by/3.0/">Creative Commons Attribution License 3.0</md:license>  <md:language>da</md:language>              <md:uuid>feda4909-5bbd-431e-a017-049aff54416d</md:uuid>
<md:slug>madlavning</md:slug>
</metadata>  <col:content>          <col:module document="m41237"/>                            <col:module document="m41241"/>                            <col:module document="m41238"/>                            <col:module document="m41298"/>                    </col:content></col:collection>